gwdatalens/__init__.py
gwdatalens/cli.py
gwdatalens/django_copy.py
gwdatalens/version.py
gwdatalens/app/app.py
gwdatalens/app/config.toml
gwdatalens/app/database_template.toml
gwdatalens/app/main.py
gwdatalens/app/settings.py
gwdatalens/app/callbacks/__init__.py
gwdatalens/app/callbacks/general.py
gwdatalens/app/callbacks/models.py
gwdatalens/app/callbacks/overview.py
gwdatalens/app/callbacks/qc.py
gwdatalens/app/callbacks/result.py
gwdatalens/app/src/cache.py
gwdatalens/app/src/utils.py
gwdatalens/app/src/components/__init__.py
gwdatalens/app/src/components/button_help_modal.py
gwdatalens/app/src/components/ids.py
gwdatalens/app/src/components/layout.py
gwdatalens/app/src/components/model_buttons.py
gwdatalens/app/src/components/model_dropdown.py
gwdatalens/app/src/components/model_plots.py
gwdatalens/app/src/components/overview_chart.py
gwdatalens/app/src/components/overview_map.py
gwdatalens/app/src/components/overview_table.py
gwdatalens/app/src/components/qc_chart.py
gwdatalens/app/src/components/qc_dropdowns.py
gwdatalens/app/src/components/qc_results_table.py
gwdatalens/app/src/components/qc_rules_form.py
gwdatalens/app/src/components/qc_traval_buttons.py
gwdatalens/app/src/components/styling.py
gwdatalens/app/src/components/tab_model.py
gwdatalens/app/src/components/tab_overview.py
gwdatalens/app/src/components/tab_qc.py
gwdatalens/app/src/components/tab_qc_result.py
gwdatalens/app/src/components/tabs.py
gwdatalens/app/src/data/__init__.py
gwdatalens/app/src/data/datamodel.py
gwdatalens/app/src/data/interface.py
gwdatalens/app/src/data/qc_definitions.py
gwdatalens/app/src/data/source.py
gwdatalens/app/src/data/traval.py
gwdatalens/app/src/data/util.py
gwdatalens/assets/custom.css
gwdatalens/assets/qc_dashboard_help.md
gwdatalens/assets/locale/general.en.yml
gwdatalens/assets/locale/general.nl.yml
gwdatalens/data/example_obscollection.zip
gwdatalens/django/__init__.py
gwdatalens/django/plotly_settings.py
gwdatalens/django/routing.py
gwdatalens/django/urls.py
gwdatalens-0.2.5.dist-info/LICENSE
gwdatalens-0.2.5.dist-info/METADATA
gwdatalens-0.2.5.dist-info/WHEEL
gwdatalens-0.2.5.dist-info/entry_points.txt
gwdatalens-0.2.5.dist-info/top_level.txt
gwdatalens-0.2.5.dist-info/RECORD
