Metadata-Version: 2.1
Name: gwdatalens
Version: 0.2.5
Summary: Dashboard for groundwater time series validation.
Author: D.A. Brakenhoff, R.C. Caljé
Maintainer-email: "D.A. Brakenhoff" <d.brakenhoff@artesia-water.nl>
License: GNU AFFERO GENERAL PUBLIC LICENSE
Project-URL: homepage, https://github.com/ArtesiaWater/gwdatalens
Project-URL: repository, https://github.com/ArtesiaWater/gwdatalens
Keywords: hydrology,dashboard,time series,error detection,validation,analysis,plotly,dash
Classifier: Development Status :: 4 - Beta
Classifier: Intended Audience :: Science/Research
Classifier: Intended Audience :: Other Audience
Classifier: License :: OSI Approved :: GNU Affero General Public License v3 or later (AGPLv3+)
Classifier: Operating System :: Microsoft :: Windows
Classifier: Operating System :: POSIX
Classifier: Operating System :: Unix
Classifier: Operating System :: MacOS
Classifier: Programming Language :: Python
Classifier: Programming Language :: Python :: 3
Classifier: Programming Language :: Python :: 3.10
Classifier: Programming Language :: Python :: 3.11
Classifier: Programming Language :: Python :: 3.12
Classifier: Programming Language :: Python :: 3 :: Only
Classifier: Topic :: Scientific/Engineering :: Hydrology
Requires-Python: >=3.10
License-File: LICENSE
Requires-Dist: numpy
Requires-Dist: geopandas
Requires-Dist: matplotlib
Requires-Dist: tqdm
Requires-Dist: dash
Requires-Dist: dash-bootstrap-components
Requires-Dist: waitress
Requires-Dist: flask-caching
Requires-Dist: tomli
Requires-Dist: sqlalchemy
Requires-Dist: i18nice[yaml]
Requires-Dist: pastastore
Requires-Dist: hydropandas
Requires-Dist: traval
Provides-Extra: lint
Requires-Dist: black ; extra == 'lint'
Requires-Dist: flake8 ; extra == 'lint'
Requires-Dist: isort ; extra == 'lint'
Requires-Dist: docformatter ; extra == 'lint'
Provides-Extra: postgresql
Requires-Dist: psycopg2 ; extra == 'postgresql'
